ipsy/__init__.py
ipsy/__main__.py
ipsy/ipsy.py
ipsy-0.1.dist-info/DESCRIPTION.rst
ipsy-0.1.dist-info/METADATA
ipsy-0.1.dist-info/RECORD
ipsy-0.1.dist-info/WHEEL
ipsy-0.1.dist-info/entry_points.txt
ipsy-0.1.dist-info/metadata.json
ipsy-0.1.dist-info/top_level.txt
